django_view_models/models.py
django_view_models/utils.py
django_view_models/__pycache__/models.cpython-36.pyc
django_view_models/__pycache__/models.cpython-37.pyc
django_view_models/__pycache__/utils.cpython-36.pyc
django_view_models/__pycache__/utils.cpython-37.pyc
django_view_models/management/commands/create_view_models.py
django_view_models/management/commands/refresh_view_models.py
django_view_models/management/commands/sync_view_models.py
django_view_models/management/commands/__pycache__/sync_view_models.cpython-36.pyc
django_view_models/management/commands/__pycache__/sync_view_models.cpython-37.pyc
django_view_models-0.1.0.dist-info/LICENSE
django_view_models-0.1.0.dist-info/METADATA
django_view_models-0.1.0.dist-info/WHEEL
django_view_models-0.1.0.dist-info/top_level.txt
django_view_models-0.1.0.dist-info/RECORD
