Metadata-Version: 2.1
Name: django-view-models
Version: 0.1.0
Summary: Django models backed by database views
Home-page: https://github.com/quadrant-newmedia/django_view_models
Author: Alex Fischer
Author-email: alex@quadrant.net
License: UNKNOWN
Platform: UNKNOWN
Classifier: Programming Language :: Python :: 3
Classifier: License :: OSI Approved :: MIT License
Classifier: Operating System :: OS Independent
Requires-Python: >=3.7
Requires-Dist: Django (<6,>=3)
